kraken_boilerplate/__init__.py
kraken_boilerplate/class_kraken_boilerplate.py
kraken_boilerplate/class_kraken_boilerplates.py
kraken_boilerplate/flask_routes.py
kraken_boilerplate/kraken_boilerplate.py
kraken_boilerplate/helpers/__init__.py
kraken_boilerplate/helpers/dot_notation.py
kraken_boilerplate/helpers/json.py
kraken_boilerplate-0.0.2.dist-info/LICENSE.txt
kraken_boilerplate-0.0.2.dist-info/METADATA
kraken_boilerplate-0.0.2.dist-info/WHEEL
kraken_boilerplate-0.0.2.dist-info/top_level.txt
kraken_boilerplate-0.0.2.dist-info/RECORD
