Metadata-Version: 2.1
Name: kraken-boilerplate
Version: 0.0.2
Summary: kraken-boilerplate
Home-page: https://github.com/tactik8/krakenboilerplate
Author: Tactik8
Author-email: info@tactik8.com
License: MIT
Classifier: License :: OSI Approved :: MIT License
Classifier: Programming Language :: Python :: 3
Classifier: Programming Language :: Python :: 3.10
License-File: LICENSE.txt
Requires-Dist: kraken-thing
Requires-Dist: requests
